tassosgeomath/__init__.py
tassosgeomath/calculator.py
tassosgeomath-2.0.0.dist-info/LICENCE
tassosgeomath-2.0.0.dist-info/METADATA
tassosgeomath-2.0.0.dist-info/WHEEL
tassosgeomath-2.0.0.dist-info/top_level.txt
tassosgeomath-2.0.0.dist-info/RECORD
