Metadata-Version: 2.1
Name: tassosgeomath
Version: 2.0.0
Summary: This is my geometry calculator package
Home-page: 
Author: Tasso
Requires-Python: >3.6
License-File: LICENCE
